sphinxcontrib_domaintools-0.3-py3.8-nspkg.pth
sphinxcontrib/domaintools/__init__.py
sphinxcontrib/domaintools/_version.py
sphinxcontrib_domaintools-0.3.dist-info/LICENSE.txt
sphinxcontrib_domaintools-0.3.dist-info/METADATA
sphinxcontrib_domaintools-0.3.dist-info/WHEEL
sphinxcontrib_domaintools-0.3.dist-info/namespace_packages.txt
sphinxcontrib_domaintools-0.3.dist-info/top_level.txt
sphinxcontrib_domaintools-0.3.dist-info/RECORD
