Metadata-Version: 1.1
Name: sphinxcontrib-domaintools
Version: 0.3
Summary: Sphinx extension for easy domain creation.
Home-page: http://bitbucket.org/klorenz/sphinxcontrib-domaintools
Author: Kay-Uwe (Kiwi) Lorenz
Author-email: kiwi@franka.dyndns.org
License: BSD
Download-URL: http://pypi.python.org/pypi/sphinxcontrib-domaintools
Platform: any
Classifier: Development Status :: 4 - Beta
Classifier: Environment :: Console
Classifier: Environment :: Web Environment
Classifier: Intended Audience :: Developers
Classifier: License :: OSI Approved :: BSD License
Classifier: Operating System :: OS Independent
Classifier: Programming Language :: Python
Classifier: Topic :: Documentation
Classifier: Topic :: Utilities
